{"type": "Feature", "id": 12513654, "geometry": {"type": "Point", "coordinates": [92.709663, 11.69201]}, "properties": {"woe:id": 12513654, "woe:parent_id": 2295345, "woe:name": "Vir Savarkar Airport", "woe:placetype": 14, "woe:placetype_name": "Airport", "woe:lang": "ENG", "iso:country": "IN", "meta:provider": ["geoplanet:7.3.1", "geoplanet:7.3.2", "geoplanet:7.4.0", "geoplanet:7.4.1", "geoplanet:7.5.1", "geoplanet:7.5.2", "geoplanet:7.6.0", "geoplanet:7.8.1", "geoplanet:7.9.0", "geoplanet:7.10.0", "geoplanet:8.0.0", "woeplanet:8.0.0"], "meta:indexed": "2020-08-20T20:24:46.119285", "woe:alias_ENG_V": ["IXZ Airport", "Port Blair Airport", "IXZ", "Pt Blair Airport"], "meta:updated": "2020-10-14T11:25:12.918008", "woe:hierarchy": {"continent": 24865671, "country": 23424848, "town": 0, "planet": 1, "county": 56558083, "suburb": 0, "state": 2345739, "region": 0, "localadmin": 0}, "woe:timezone_id": 28350818, "woe:hash": "w41ft8mngsxh", "woe:centroid": [92.709663, 11.69201], "geom:latitude": 11.69201, "geom:longitude": 92.709663, "geom:hash": "w41ft8mngsxh", "woe:latitude": 11.69201, "geom:centroid": [92.709663, 11.69201], "woe:longitude": 92.709663, "woe:repo": "woeplanet-airport-in", "geom:area": 0.0, "woe:scale": 19}}