{"type": "Feature", "id": 12513528, "geometry": {"type": "Point", "coordinates": [77.978798, 27.163231]}, "properties": {"woe:id": 12513528, "woe:parent_id": 29093795, "woe:name": "Agra Airport", "woe:placetype": 14, "woe:placetype_name": "Airport", "woe:lang": "ENG", "iso:country": "IN", "meta:provider": ["geoplanet:7.3.1", "geoplanet:7.3.2", "geoplanet:7.4.0", "geoplanet:7.4.1", "geoplanet:7.5.1", "geoplanet:7.5.2", "geoplanet:7.6.0", "geoplanet:7.8.1", "geoplanet:7.9.0", "geoplanet:7.10.0", "geoplanet:8.0.0", "woeplanet:8.0.0"], "meta:indexed": "2020-08-20T20:24:46.033666", "woe:alias_ENG_V": ["AGR Airport", "AGR"], "meta:updated": "2020-10-14T11:25:12.885160", "woe:hierarchy": {"continent": 24865671, "country": 23424848, "town": 0, "planet": 1, "county": 12586712, "suburb": 0, "state": 2345760, "region": 0, "localadmin": 0}, "woe:timezone_id": 28350818, "woe:hash": "tsz6w2ymm9q0", "woe:centroid": [77.978798, 27.163231], "geom:latitude": 27.163231, "geom:longitude": 77.978798, "geom:hash": "tsz6w2ymm9q0", "woe:latitude": 27.163231, "geom:centroid": [77.978798, 27.163231], "woe:longitude": 77.978798, "woe:repo": "woeplanet-airport-in", "geom:area": 0.0, "woe:scale": 19}}