{"type": "Feature", "id": 29230264, "geometry": {"type": "Point", "coordinates": [88.612587, 27.33577]}, "properties": {"woe:id": 29230264, "woe:parent_id": 29074267, "woe:name": "Gangtok Airport", "woe:placetype": 14, "woe:placetype_name": "Airport", "woe:lang": "ENG", "iso:country": "IN", "meta:provider": ["geoplanet:7.3.1", "geoplanet:7.3.2", "geoplanet:7.4.0", "geoplanet:7.4.1", "geoplanet:7.5.1", "geoplanet:7.5.2", "geoplanet:7.6.0", "geoplanet:7.8.1", "geoplanet:7.9.0", "geoplanet:7.10.0", "geoplanet:8.0.0", "woeplanet:8.0.0"], "meta:indexed": "2020-08-20T20:24:46.156584", "meta:updated": "2020-10-14T11:25:12.845090", "woe:hierarchy": {"continent": 24865671, "country": 23424848, "town": 0, "planet": 1, "county": 12586813, "suburb": 0, "state": 2345762, "region": 0, "localadmin": 0}, "woe:timezone_id": 28350818, "woe:hash": "tuz582mdquvg", "woe:centroid": [88.612587, 27.33577], "geom:latitude": 27.33577, "geom:longitude": 88.612587, "geom:hash": "tuz582mdquvg", "woe:latitude": 27.33577, "geom:centroid": [88.612587, 27.33577], "woe:longitude": 88.612587, "woe:repo": "woeplanet-airport-in", "geom:area": 0.0, "woe:scale": 19}}