{"type": "Feature", "id": 12513567, "properties": {"woe:id": 12513567, "woe:parent_id": 29165084, "woe:name": "Chapra Airport", "woe:placetype": 14, "woe:placetype_name": "Airport", "woe:lang": "ENG", "iso:country": "IN", "meta:provider": ["geoplanet:7.3.1", "geoplanet:7.3.2", "geoplanet:7.4.0", "geoplanet:7.4.1", "geoplanet:7.5.1", "geoplanet:7.5.2", "geoplanet:7.6.0", "geoplanet:7.8.1", "geoplanet:7.9.0", "geoplanet:7.10.0", "geoplanet:8.0.0", "woeplanet:8.0.0"], "meta:indexed": "2020-08-20T20:24:46.059842", "meta:updated": "2020-08-22T02:01:44.896912", "woe:hierarchy": {"continent": 24865671, "country": 23424848, "town": 0, "planet": 1, "county": 12586411, "suburb": 0, "state": 2345742, "region": 0, "localadmin": 0}, "woe:timezone_id": 28350818, "woe:hash": "tus68vs1yw4t", "woe:centroid": [84.765297, 25.782499], "geom:latitude": 25.782499, "geom:longitude": 84.765297, "geom:hash": "tus68vs1yw4t", "woe:latitude": 25.782499, "geom:centroid": [84.765297, 25.782499], "woe:longitude": 84.765297, "woe:repo": "woeplanet-airport-in"}, "geometry": {"coordinates": [84.765297, 25.782499], "type": "Point"}}