{"type": "Feature", "id": 12515269, "geometry": {"type": "Point", "coordinates": [75.540001, 35.330002]}, "properties": {"woe:id": 12515269, "woe:parent_id": 2209890, "woe:name": "Skardu Airport", "woe:placetype": 14, "woe:placetype_name": "Airport", "woe:lang": "ENG", "iso:country": "IN", "meta:provider": ["geoplanet:7.3.1", "geoplanet:7.3.2", "geoplanet:7.4.0", "geoplanet:7.4.1", "geoplanet:7.5.1", "geoplanet:7.5.2", "geoplanet:7.6.0", "geoplanet:7.8.1", "geoplanet:7.9.0", "geoplanet:7.10.0", "geoplanet:8.0.0", "woeplanet:8.0.0"], "meta:indexed": "2020-08-20T20:24:46.151864", "woe:alias_ENG_V": ["KDU", "KDU Airport"], "meta:updated": "2020-10-14T11:25:12.895641", "woe:hierarchy": {"continent": 24865671, "country": 23424848, "town": 0, "planet": 1, "county": 12586457, "suburb": 0, "state": 2345746, "region": 0, "localadmin": 0}, "woe:timezone_id": 28350818, "woe:hash": "twm8yzws1ter", "woe:centroid": [75.540001, 35.330002], "geom:latitude": 35.330002, "geom:longitude": 75.540001, "geom:hash": "twm8yzws1ter", "woe:latitude": 35.330002, "geom:centroid": [75.540001, 35.330002], "woe:longitude": 75.540001, "woe:repo": "woeplanet-airport-in", "geom:area": 0.0, "woe:scale": 19}}