{"type": "Feature", "id": 12513561, "geometry": {"type": "Point", "coordinates": [88.438744, 22.65255]}, "properties": {"woe:id": 12513561, "woe:parent_id": 29016940, "woe:name": "Netaji Subhash Chandra Bose International Airport", "woe:placetype": 14, "woe:placetype_name": "Airport", "woe:lang": "ENG", "iso:country": "IN", "meta:provider": ["geoplanet:7.3.1", "geoplanet:7.3.2", "geoplanet:7.4.0", "geoplanet:7.4.1", "geoplanet:7.5.1", "geoplanet:7.5.2", "geoplanet:7.6.0", "geoplanet:7.8.1", "geoplanet:7.9.0", "geoplanet:7.10.0", "geoplanet:8.0.0", "woeplanet:8.0.0"], "meta:indexed": "2020-08-20T20:24:46.167258", "woe:alias_ENG_V": ["Netaji Subhash Chandra Int'l Arp", "Dum Dum Airport", "Calcutta Airport", "CCU", "CCU Airport", "Kolkata Airport", "Calcutta International Airport", "Kolkata International Airport"], "meta:updated": "2020-10-14T11:25:12.864704", "woe:hierarchy": {"continent": 24865671, "country": 23424848, "town": 0, "planet": 1, "county": 12586808, "suburb": 0, "state": 2345761, "region": 0, "localadmin": 0}, "woe:timezone_id": 28350818, "woe:hash": "tunbu7z0sj7h", "woe:centroid": [88.438744, 22.65255], "geom:latitude": 22.65255, "geom:longitude": 88.438744, "geom:hash": "tunbu7z0sj7h", "woe:latitude": 22.65255, "geom:centroid": [88.438744, 22.65255], "woe:longitude": 88.438744, "woe:repo": "woeplanet-airport-in", "geom:area": 0.0, "woe:scale": 19}}