{"type": "Feature", "id": 12513625, "geometry": {"type": "Point", "coordinates": [92.51667, 24.966669]}, "properties": {"woe:id": 12513625, "woe:parent_id": 29154006, "woe:name": "Kumbhirgram Airport", "woe:placetype": 14, "woe:placetype_name": "Airport", "woe:lang": "ENG", "iso:country": "IN", "meta:provider": ["geoplanet:7.3.1", "geoplanet:7.3.2", "geoplanet:7.4.0", "geoplanet:7.4.1", "geoplanet:7.5.1", "geoplanet:7.5.2", "geoplanet:7.6.0", "geoplanet:7.8.1", "geoplanet:7.9.0", "geoplanet:7.10.0", "geoplanet:8.0.0", "woeplanet:8.0.0"], "meta:indexed": "2020-08-20T20:24:46.100767", "woe:alias_ENG_V": ["IXS Airport", "Silchar Airport", "IXS"], "meta:updated": "2020-10-14T11:25:12.903430", "woe:hierarchy": {"continent": 24865671, "country": 23424848, "town": 0, "planet": 1, "county": 12586351, "suburb": 0, "state": 2345741, "region": 0, "localadmin": 0}, "woe:timezone_id": 28350818, "woe:hash": "wh3y13096smj", "woe:centroid": [92.51667, 24.966669], "geom:latitude": 24.966669, "geom:longitude": 92.51667, "geom:hash": "wh3y13096smj", "woe:latitude": 24.966669, "geom:centroid": [92.51667, 24.966669], "woe:longitude": 92.51667, "woe:repo": "woeplanet-airport-in", "geom:area": 0.0, "woe:scale": 19}}