{"type": "Feature", "id": 12513579, "geometry": {"type": "Point", "coordinates": [86.433296, 23.8367]}, "properties": {"woe:id": 12513579, "woe:parent_id": 29201517, "woe:name": "Dhanbad Airport", "woe:placetype": 14, "woe:placetype_name": "Airport", "woe:lang": "ENG", "iso:country": "IN", "meta:provider": ["geoplanet:7.3.1", "geoplanet:7.3.2", "geoplanet:7.4.0", "geoplanet:7.4.1", "geoplanet:7.5.1", "geoplanet:7.5.2", "geoplanet:7.6.0", "geoplanet:7.8.1", "geoplanet:7.9.0", "geoplanet:7.10.0", "geoplanet:8.0.0", "woeplanet:8.0.0"], "meta:indexed": "2020-08-20T20:24:46.068465", "woe:alias_ENG_V": ["DBD", "DBD Airport"], "meta:updated": "2020-10-14T11:25:12.894048", "woe:hierarchy": {"continent": 24865671, "country": 23424848, "town": 0, "planet": 1, "county": 12586380, "suburb": 0, "state": 20070463, "region": 0, "localadmin": 0}, "woe:timezone_id": 28350818, "woe:hash": "tujrwg6fcfbw", "woe:centroid": [86.433296, 23.8367], "geom:latitude": 23.8367, "geom:longitude": 86.433296, "geom:hash": "tujrwg6fcfbw", "woe:latitude": 23.8367, "geom:centroid": [86.433296, 23.8367], "woe:longitude": 86.433296, "woe:repo": "woeplanet-airport-in", "geom:area": 0.0, "woe:scale": 19}}