{"type": "Feature", "id": 12513583, "properties": {"woe:id": 12513583, "woe:parent_id": 29214744, "woe:name": "Fukche Airport", "woe:placetype": 14, "woe:placetype_name": "Airport", "woe:lang": "ENG", "iso:country": "IN", "meta:provider": ["geoplanet:7.3.1", "geoplanet:7.3.2", "geoplanet:7.4.0", "geoplanet:7.4.1", "geoplanet:7.5.1", "geoplanet:7.5.2", "geoplanet:7.6.0", "geoplanet:7.8.1", "geoplanet:7.9.0", "geoplanet:7.10.0", "geoplanet:8.0.0", "woeplanet:8.0.0"], "meta:indexed": "2020-08-20T20:24:46.071466", "meta:updated": "2020-08-22T02:01:44.902308", "woe:hierarchy": {"continent": 24865671, "country": 23424848, "town": 0, "planet": 1, "county": 12586457, "suburb": 0, "state": 2345746, "region": 0, "localadmin": 0}, "woe:timezone_id": 28350818, "woe:hash": "tvb76tbncg0f", "woe:centroid": [79.211502, 32.9478], "geom:latitude": 32.9478, "geom:longitude": 79.211502, "geom:hash": "tvb76tbncg0f", "woe:latitude": 32.9478, "geom:centroid": [79.211502, 32.9478], "woe:longitude": 79.211502, "woe:repo": "woeplanet-airport-in"}, "geometry": {"coordinates": [79.211502, 32.9478], "type": "Point"}}