{"type": "Feature", "id": 29230267, "geometry": {"type": "Point", "coordinates": [79.599998, 17.91785]}, "properties": {"woe:id": 29230267, "woe:parent_id": 29139202, "woe:name": "Warangal Airport", "woe:placetype": 14, "woe:placetype_name": "Airport", "woe:lang": "ENG", "iso:country": "IN", "meta:provider": ["geoplanet:7.3.1", "geoplanet:7.3.2", "geoplanet:7.4.0", "geoplanet:7.4.1", "geoplanet:7.5.1", "geoplanet:7.5.2", "geoplanet:7.6.0", "geoplanet:7.8.1", "geoplanet:7.9.0", "geoplanet:7.10.0", "geoplanet:8.0.0", "woeplanet:8.0.0"], "meta:indexed": "2020-08-20T20:24:46.158925", "meta:updated": "2020-10-14T11:25:12.848940", "woe:hierarchy": {"continent": 24865671, "country": 23424848, "town": 0, "planet": 1, "county": 12586348, "suburb": 0, "state": 2345740, "region": 0, "localadmin": 0}, "woe:timezone_id": 28350818, "woe:hash": "tg0tgmfgn3k6", "woe:centroid": [79.599998, 17.91785], "geom:latitude": 17.91785, "geom:longitude": 79.599998, "geom:hash": "tg0tgmfgn3k6", "woe:latitude": 17.91785, "geom:centroid": [79.599998, 17.91785], "woe:longitude": 79.599998, "woe:repo": "woeplanet-airport-in", "geom:area": 0.0, "woe:scale": 19}}